{
  "seq_trpb_documento": 17,
  "desc_titulo_documento": "AQUISIÇÃO",
  "ano_doc_trpb": 2018,
  "num_doc_trpb": 11,
  "nome_unidade": "Coordenadoria de Planejamento Estratégico",
  "sg_unidade": "CPES",
  "seq_id_unid_sup": 1650,
  "ind_niv_hierc": "2",
  "seq_processo": null,
  "ind_trpb_tp_documento": "2",
  "ind_trpb_st_documento": "1",
  "ind_trpb_doc_modelo": "1",
  "ind_trpb_tp_modelo": "1",
  "ind_trpb_st_edicao_doc": "9",
  "ind_trpb_area_modelo": "0",
  "ind_st_registro": "0",
  "dt_registro": "2018-09-11T00:00:00.000Z",
  "cod_usuario": "elainen",
  "dt_alteracao": "2018-09-14T15:39:20.117Z",
  "cod_usuario_alteracao": "elainen",
  "seq_pedido_material": null,
  "ind_trpb_migrou_modelo": "0",
  "contrato": "11/2018",
  "texto": "OBJETO\nAquisição de solução para realizar a gestão estratégica, baseada na metodologia BSC, no âmbito do STJ, contendo: 3 2.1 Sistema instalado (engine do software), além de eventual conjunto de softwares acessórios necessários ao seu funcionamento bem como respectivas licenças cadastradas em nome do STJ. 2.2 Serviço de implementação do software. 2.3 Transferência de conhecimento técnico sobre a solução com capacitação da equipe técnica de TI, administradores e usuários. 2.4 Garantia, atualização de versão e suporte técnico sobre tecnologia ou negócio da solução ofertada com número ilimitado de chamados para a resolução de problemas técnicos durante o período de 24 meses a contar da instalação.\nJUSTIFICATIVA\nO Superior Tribunal de Justiça (STJ) utiliza o planejamento estratégico como ferramenta de gestão desde 1998, tendo adotado a metodologia do Balanced Scorecard (BSC) em 2004. O BSC baseia-se na gestão do desempenho por meio de indicadores, na comunicação dos resultados e no equilíbrio e relação de causa e efeito entre os objetivos estratégicos voltados para o desenvolvimento dos ativos tangíveis e intangíveis da organização. Apesar de possuir um plano quinquenal desde 2010, a gestão estratégica do STJ ainda carece de uma ferramenta para monitorar a implementação efetiva do Plano Estratégico nas unidades da Corte. Em 2004, foi adquirido o software Isosystem que permaneceu em uso até 6/1/2009, quando a Coordenadoria de Planejamento Estratégico se manifestou pela não prorrogação do contrato, tendo em vista a obsolescência do desenvolvimento da ferramenta frente à evolução da gestão estratégica neste Tribunal. A partir de então, os indicadores são acompanhados e medidos via planilhas em Excel que são alimentadas manualmente pelos respectivos gestores, o que dificulta o gerenciamento das informações (devido à grande quantidade de dados e a impossibilidade de edição compartilhada dos arquivos), prejudica o processo de decisão (inexistência de painéis de controle e relatórios/gráficos automáticos, ausência de registro de ações corretivas etc.), além de comprometer a segurança da informação (maior possibilidade de erro humano e de perda/alteração de dados). Apesar de não possuir sistema informatizado de apoio ao gerenciamento, o modelo de gestão estratégica evoluiu a partir do início de 2012, quando iniciaram as ações do projeto Alinhamento Estratégico, que busca desdobrar os objetivos do Plano Estratégico em todas as unidades do Tribunal. Dessa forma, tendo em vista o significativo aumento da quantidade de informações a serem registradas e acompanhadas, ficou ainda mais evidenciada a necessidade de uma solução tecnológica para apoiar a medição, o monitoramento, a análise, a mobilização e a comunicação das estratégias definidas. Outra questão que segue prejudicada com a atual metodologia é a mensuração das metas nacionais acompanhadas pelo Conselho Nacional de Justiça. Tais metas são, em sua maioria, extraídas por selects executados pela STI diretamente no banco de dados do Sistema Justiça. Esses procedimentos geralmente têm que ser executados durante a madrugada para não sobrecarregar os sistemas. Tal situação não proporciona autonomia à AMG, unidade responsável pelas informações, para acessar os dados quando demandados pela alta administração ou pelo CNJ. Portanto, a aquisição de Licença de Software para gestão estratégica incluindo serviços de instalação, configuração, suporte técnico e atualização de versões trará como benefícios: Contribuir para a gestão da estratégia do STJ, facilitando a gestão e mensuração de indicadores, objetivos e, de forma geral, a concretização do Plano Estratégico em execução. Monitorar a implantação dos planos setoriais nas diversas unidades do Tribunal, proporcionando facilidades na extração e mensuração de indicadores, bem como fortalecendo a segurança das informações. Ampliar e aperfeiçoar a comunicação dos resultados da gestão estratégica do STJ pela exportação de dados e gráficos gerados no sistema. Avaliar e implementar processos de melhoria contínua pela análise dos resultados alcançados, proposição de ações corretivas em planos de ação que possam ser acompanhados. Traduzir a estratégia para os níveis operacionais por meio do desdobramento de objetivos estratégicos e indicadores. Propiciar a disseminação de melhores práticas e lições aprendidas na implementação de projetos estratégicos pela interação entre as unidades.\nESPECIFICAÇÃO DO OBJETO\nAquisição de solução para realizar a gestão estratégica, baseada na metodologia BSC, no âmbito do STJ, contendo: 2.1 Sistema instalado (engine do software), além de eventual conjunto de softwares acessórios necessários ao seu funcionamento bem como respectivas licenças cadastradas em nome do STJ. 2.2 Serviço de implementação do software. 2.3 Transferência de conhecimento técnico sobre a solução com capacitação da equipe técnica de TI, administradores e usuários. 2.4 Garantia, atualização de versão e suporte técnico sobre tecnologia ou negócio da solução ofertada com número ilimitado de chamados para a resolução de problemas técnicos durante o período de 24 meses a contar da instalação.\nQUANTITATIVO ESTIMADO\npacote de licenças deverá permitir 30 acessos simultâneos bem como atender aos seguintes potenciais usuários: 3.2.1. 25 usuários administradores. 3.2.2. 10 usuários técnicos. 3.2.3. 100 usuários das áreas de negócio 3.2.4. Acesso a leitura ilimitado.\nFORMA DE ADJUDICAÇÃO\nO pagamento dar-se-á ao por crédito bancário em até 30 dias após o recebimento do produto ou serviço. 9.2. O pagamento das etapas 1, 2 e 3 será realizado na finalização do serviço a ser atestado pela emissão dos termos de aceite. 9.3. No caso das etapas 4 o pagamento será realizado mensalmente.\nSANÇÕES\nPAGAMENTO\nO pagamento dar-se-á ao por crédito bancário em até 30 dias após o recebimento do produto ou serviço. 9.2. O pagamento das etapas 1, 2 e 3 será realizado na finalização do serviço a ser atestado pela emissão dos termos de aceite. 9.3. No caso das etapas 4 o pagamento será realizado mensalmente.\nFISCALIZAÇÃO\nESTIMATIVA\n",
  "textoFormatado": "<h1>OBJETO</h1>\n<p>Aquisição de solução para realizar a gestão estratégica, baseada na metodologia<br /> BSC, no âmbito do STJ, contendo:<br /> 3<br /> 2.1 Sistema instalado (engine do software), além de eventual conjunto de softwares acessórios necessários ao seu funcionamento bem como respectivas licenças cadastradas em nome do STJ.<br /> 2.2 Serviço de implementação do software.<br /> 2.3 Transferência de conhecimento técnico sobre a solução com capacitação da equipe técnica de TI, administradores e usuários.<br /> 2.4 Garantia, atualização de versão e suporte técnico sobre tecnologia ou negócio da solução ofertada com número ilimitado de chamados para a resolução de problemas técnicos durante o período de 24 meses a contar da instalação.</p> \n<p>&nbsp;</p>\n<h1>JUSTIFICATIVA</h1>\n<p>O Superior Tribunal de Justiça (STJ) utiliza o planejamento estratégico como ferramenta de gestão desde 1998, tendo adotado a metodologia do Balanced Scorecard (BSC) em 2004. O BSC baseia-se na gestão do desempenho por meio de indicadores, na comunicação dos resultados e no equilíbrio e relação de causa e efeito entre os objetivos estratégicos voltados para o desenvolvimento dos ativos tangíveis e intangíveis da organização.<br /> Apesar de possuir um plano quinquenal desde 2010, a gestão estratégica do STJ ainda carece de uma ferramenta para monitorar a implementação efetiva do Plano Estratégico nas unidades da Corte.<br /> Em 2004, foi adquirido o software Isosystem que permaneceu em uso até 6/1/2009, quando a Coordenadoria de Planejamento Estratégico se manifestou pela não prorrogação do contrato, tendo em vista a obsolescência do desenvolvimento da ferramenta frente à evolução da gestão estratégica neste Tribunal.<br /> A partir de então, os indicadores são acompanhados e medidos via planilhas em Excel que são alimentadas manualmente pelos respectivos gestores, o que dificulta o gerenciamento das informações (devido à grande quantidade de dados e a impossibilidade de edição compartilhada dos arquivos), prejudica o processo de decisão (inexistência de painéis de controle e relatórios/gráficos automáticos, ausência de registro de ações corretivas etc.), além de comprometer a segurança da informação (maior possibilidade de erro humano e de perda/alteração de dados).<br /> Apesar de não possuir sistema informatizado de apoio ao gerenciamento, o modelo de gestão estratégica evoluiu a partir do início de 2012, quando iniciaram as ações do projeto Alinhamento Estratégico, que busca desdobrar os objetivos do Plano Estratégico em todas as unidades do Tribunal. Dessa forma, tendo em vista o significativo aumento da quantidade de informações a serem registradas e acompanhadas, ficou ainda mais evidenciada a necessidade de uma solução&nbsp;tecnológica para apoiar a medição, o monitoramento, a análise, a mobilização e a comunicação das estratégias definidas.<br /> Outra questão que segue prejudicada com a atual metodologia é a mensuração das metas nacionais acompanhadas pelo Conselho Nacional de Justiça. Tais metas são, em sua maioria, extraídas por selects executados pela STI diretamente no banco de dados do Sistema Justiça. Esses procedimentos geralmente têm que ser executados durante a madrugada para não sobrecarregar os sistemas. Tal situação não proporciona autonomia à AMG, unidade responsável pelas informações, para acessar os dados quando demandados pela alta administração ou pelo CNJ.<br /> Portanto, a aquisição de Licença de Software para gestão estratégica incluindo serviços de instalação, configuração, suporte técnico e atualização de versões trará como benefícios:<br /> Contribuir para a gestão da estratégia do STJ, facilitando a gestão e mensuração de indicadores, objetivos e, de forma geral, a concretização do Plano Estratégico em execução.<br /> Monitorar a implantação dos planos setoriais nas diversas unidades do Tribunal, proporcionando facilidades na extração e mensuração de indicadores, bem como fortalecendo a segurança das informações.<br /> Ampliar e aperfeiçoar a comunicação dos resultados da gestão estratégica do STJ pela exportação de dados e gráficos gerados no sistema.<br /> Avaliar e implementar processos de melhoria contínua pela análise dos resultados alcançados, proposição de ações corretivas em planos de ação que possam ser acompanhados.<br /> Traduzir a estratégia para os níveis operacionais por meio do desdobramento de objetivos estratégicos e indicadores.<br /> Propiciar a disseminação de melhores práticas e lições aprendidas na implementação de projetos estratégicos pela interação entre as unidades.</p>\n<h1>ESPECIFICAÇÃO DO OBJETO</h1>\n<p>Aquisição de solução para realizar a gestão estratégica, baseada na metodologia BSC, no âmbito do STJ, contendo:</p> \n<p>2.1 Sistema instalado (engine do software), além de eventual conjunto de softwares acessórios necessários ao seu funcionamento bem como respectivas licenças cadastradas em nome do STJ.<br /> 2.2 Serviço de implementação do software.<br /> 2.3 Transferência de conhecimento técnico sobre a solução com capacitação da equipe técnica de TI, administradores e usuários.<br /> 2.4 Garantia, atualização de versão e suporte técnico sobre tecnologia ou negócio da solução ofertada com número ilimitado de chamados para a resolução de problemas técnicos durante o período de 24 meses a contar da instalação.</p>\n<h1>QUANTITATIVO ESTIMADO</h1>\n<p>pacote de licenças deverá permitir 30 acessos simultâneos bem como atender aos seguintes potenciais usuários:<br /> 3.2.1. 25 usuários administradores.<br /> 3.2.2. 10 usuários técnicos.<br /> 3.2.3. 100 usuários das áreas de negócio<br /> 3.2.4. Acesso a leitura ilimitado.</p>\n<h1>FORMA DE ADJUDICAÇÃO</h1>\n<p>O pagamento dar-se-á ao por crédito bancário em até 30 dias após o recebimento do produto ou serviço.<br /> 9.2. O pagamento das etapas 1, 2 e 3 será realizado na finalização do serviço a ser atestado pela emissão dos termos de aceite.<br /> 9.3. No caso das etapas 4 o pagamento será realizado mensalmente.</p>\n<h1>SANÇÕES</h1>\n<h1>PAGAMENTO</h1>\n<p>O pagamento dar-se-á ao por crédito bancário em até 30 dias após o recebimento do produto ou serviço.<br /> 9.2. O pagamento das etapas 1, 2 e 3 será realizado na finalização do serviço a ser atestado pela emissão dos termos de aceite.<br /> 9.3. No caso das etapas 4 o pagamento será realizado mensalmente.</p>\n<h1>FISCALIZAÇÃO</h1>\n<h1>ESTIMATIVA</h1>\n"
}